rcer_iot_client/__init__.py
rcer_iot_client/epii/__init__.py
rcer_iot_client/epii/api.py
rcer_iot_client/epii/controllers/__init__.py
rcer_iot_client/epii/controllers/update_thies_data.py
rcer_iot_client/epii/controllers/types/__init__.py
rcer_iot_client/epii/controllers/types/update_thies_data_types.py
rcer_iot_client/epii/tests/__init__.py
rcer_iot_client/epii/tests/test_api.py
rcer_iot_client/epii/tests/controllers/test_update_thies_data_controller.py
rcer_iot_client/epii/tests/use_cases/test_update_thies_data_use_case.py
rcer_iot_client/epii/use_cases/constants.py
rcer_iot_client/epii/use_cases/update_thies_data.py
rcer_iot_client/epii/use_cases/types/__init__.py
rcer_iot_client/epii/use_cases/types/update_thies_data_types.py
rcer_iot_client/epii/utils/__init__.py
rcer_iot_client/epii/utils/update_thies_data_utils.py
rcer_iot_client/general_types/__init__.py
rcer_iot_client/general_types/api/__init__.py
rcer_iot_client/general_types/api/update_thies_data_types.py
rcer_iot_client/general_types/error_types/__init__.py
rcer_iot_client/general_types/error_types/api/__init__.py
rcer_iot_client/general_types/error_types/api/update_thies_data_error_types.py
rcer_iot_client/general_types/error_types/common/__init__.py
rcer_iot_client/general_types/error_types/common/common_types.py
rcer_iot_client/libs/async_http_client/__init__.py
rcer_iot_client/libs/async_http_client/async_http_client.py
rcer_iot_client/libs/async_http_client/async_http_client_contract.py
rcer_iot_client/libs/async_http_client/clients/__init__.py
rcer_iot_client/libs/async_http_client/clients/aiohttp_client.py
rcer_iot_client/libs/async_http_client/types/__init__.py
rcer_iot_client/libs/async_http_client/types/async_http_client_types.py
rcer_iot_client/libs/ftp_client/__init__.py
rcer_iot_client/libs/ftp_client/ftp_client.py
rcer_iot_client/libs/ftp_client/ftp_client_contract.py
rcer_iot_client/libs/ftp_client/clients/__init__.py
rcer_iot_client/libs/ftp_client/clients/aioftp_client.py
rcer_iot_client-0.1.4.dist-info/METADATA
rcer_iot_client-0.1.4.dist-info/WHEEL
rcer_iot_client-0.1.4.dist-info/top_level.txt
rcer_iot_client-0.1.4.dist-info/RECORD
